funny_1965/__init__.py
funny_1965-0.1.dist-info/METADATA
funny_1965-0.1.dist-info/WHEEL
funny_1965-0.1.dist-info/top_level.txt
funny_1965-0.1.dist-info/RECORD
