Metadata-Version: 2.1
Name: funny-1965
Version: 0.1
Summary: The funniest joke in the world
Home-page: http://github.com/BeshoyAnwar/funny_1965
Author: Flying Circus
Author-email: flyingcircus@example.com
License: MIT
Platform: UNKNOWN
